[
    {
        "name": "NexCC",
        "description": "Das ist eine Beschreibung.",
        "image": "swisscom_logo.webp",
        "github": "www.github.com",
        "time": "",
        "reference": "",
        "technologies": [
            "Vue",
            "SCSS",
            "Javascript",
            "Springboot"
        ]
    },
    {
        "name": "Traily",
        "description": "Frontend Developer @Traily",
        "reference": "Dillan Conese",
        "image": "traily.webp",
        "github": "www.github.com",
        "time": "01.02.2022 - 22.07.2022",
        "technologies": [
            "Vue",
            "SCSS",
            "Javascript",
            "Springboot"
        ]
    },
    {
        "name": "MySwisscom",
        "description": "Frontend Developer bei den Avengers (R2A)",
        "image": "mySwisscom.webp",
        "github": "www.github.com",
        "time": "31.10.2022 - 31.01.2023",
        "reference": "Simon Leutwiler",
        "technologies": [
            "Vue",
            "SCSS",
            "Javascript",
            "Springboot"
        ]
    }
]